Metadata-Version: 2.1
Name: kde-wallpaper-cli
Version: 1.2.0
Summary: Set the wallpaper for KDE
Home-page: https://github.com/talwrii/kde-wallpaper-cli
Author: @readwithai
Author-email: talwrii@gmail.com
License: MIT
Keywords: KDE,wallpaper
